completion_buffer/parameters.vh
   parameter w_din = 32 ,
	       size = 8 ,
	       log2size = 3;

completion_buffer/completion_buffer.v
/*
 Completion Buffer
 
 1. Accepts writes out of order
 2. Data sent out in order
 
 Use Dual-Port Block-RAM for initial version
 
 */


module completion_buffer( /*AUTOARG*/
   // Outputs
   i_rdy, dout, dout_v,
   // Inputs
   clk, rst, din, din_v, wr_addr
   );

`include "parameters.vh"
   
   input clk,rst;
   input [w_din-1 : 0] din ;
   input 	       din_v ;
   output 	       i_rdy ; //asserted when there is space in buffer
   input [log2size-1:0]  wr_addr;
   
   output [w_din-1:0]  dout ;
   output 	       dout_v;
   
   //Memory (include entry present bit)
   reg [w_din:0]       mem [0:size-1];

   //Extra MSB bit will be used to flip polarity of 'present bit'
   //each time we go around
   reg [log2size:0]  wr_ptr,rd_ptr;
   reg [w_din-1:0]   dout_wc,dout_rc;
   
   //zReg

   reg   [log2size-1:0] entry_cnt_rc ;
   reg   [log2size:0] wr_cnt_rc ;
   reg   [log2size:0] rd_ptr_rc ;
   reg   [log2size-1:0] entry_cnt_wc ;
   reg   [log2size:0] wr_cnt_wc ;
   reg 		      dout_v_wc ,dout_v_rc;
   
   reg  vbit_rc ;
   reg   [log2size:0] rd_ptr_wc ;

   wire [w_din-1:0]  dout = dout_rc;
   wire 	     dout_v = dout_v_rc;
   
   
   //Since dual port , can decouple writes and reads
   //2 separate machines (or processes)

   //Process to track number of entries
   //Also, the total number of writes, so that I can flip
   //the valid bit
   always @(posedge clk)
     if (rst)
       begin
	  //zClkReset
	  entry_cnt_rc <= 0 ; 
	  wr_cnt_rc <= 0 ; 
	  rd_ptr_rc <= 0 ; 
       end
     else
       begin
	  //zClkAssign
	  entry_cnt_rc <=  entry_cnt_wc ; 
	  wr_cnt_rc <=  wr_cnt_wc ; 
	  rd_ptr_rc <=  rd_ptr_wc ;
	  dout_v_rc <= dout_v_wc;
       end
   
   always @(/*AUTOSENSE*/din_v or dout_v or entry_cnt_rc or wr_cnt_rc)
     begin
	entry_cnt_wc = entry_cnt_rc;
	wr_cnt_wc = wr_cnt_rc;

	if ( din_v )
	  wr_cnt_wc = wr_cnt_rc + 1;
	
	case ( {dout_v,din_v} )
	  2'b01: entry_cnt_wc  = entry_cnt_rc + 1 ;
	  2'b10: entry_cnt_wc  = entry_cnt_rc - 1 ;
	endcase // case ( {dout_v,din_v} )	
     end

   //note : comb path from din_v, registering it will cause an overflow
   //or can use almost not rdy signal
   wire i_rdy = (entry_cnt_wc != size);

   //WR process
   always @(posedge clk)
     if ( din_v & ~rst )
       //Write, assuming that din_v is well behaved w.r.t i_rdy
       //Valid bit is MSB of wr_cnt_rc flipped
       mem[wr_addr] <= { ~wr_cnt_rc[log2size] , din };

   reg 	rd_happened ;
   
   always @(posedge clk)
     if (rst)
       rd_happened <= 0;
     else
       if ( wr_addr != rd_ptr_rc[log2size-1:0] && ~rst  )
	 begin
	    {vbit_rc,dout_rc} <= mem[rd_ptr_rc[log2size-1:0]];
	    rd_happened <= 1;
	 end
       else
	 rd_happened <= 0;
     
   //RD process, 
   always @(/*AUTOSENSE*/log2size or rd_ptr_rc or vbit_rc)
     begin
	dout_v_wc = 0;
	rd_ptr_wc =  rd_ptr_rc;
	
	//polling location, making sure write not happening to the same addr	
	  begin
	     //Valid entry, push out and inc pointer
	     if ( vbit_rc == ~rd_ptr_rc[log2size] & rd_happened )
	       begin
		  rd_ptr_wc = rd_ptr_rc + 1;
		  dout_v_wc = 1;
	       end
	  end
     end
   

endmodule // completion_buffer


module tb ;

`include "parameters.vh"
   
   /*AUTOREGINPUT*/
   // Beginning of automatic reg inputs (for undeclared instantiated-module inputs)
   reg			clk;			// To dut of completion_buffer.v
   reg [w_din-1:0]	din;			// To dut of completion_buffer.v
   reg			din_v;			// To dut of completion_buffer.v
   reg			rst;			// To dut of completion_buffer.v
   reg [log2size-1:0]	wr_addr;		// To dut of completion_buffer.v
   // End of automatics

   /*AUTOWIRE*/
   // Beginning of automatic wires (for undeclared instantiated-module outputs)
   wire [w_din-1:0]	dout;			// From dut of completion_buffer.v
   wire			dout_v;			// From dut of completion_buffer.v
   wire			i_rdy;			// From dut of completion_buffer.v
   // End of automatics

   initial
     begin
	$dumpvars;

	clk=0;
	rst =1;
	din = 0;
	din_v = 0;
	wr_addr = 7;
	#105;
	@(negedge clk);	
	rst = 0;


	#10000;
	$finish;
     end // initial begin

   always #5 clk = ~clk;

   always @(posedge clk)
     if ( ~rst )
       begin
	  din <= din + 1;
	  wr_addr <= wr_addr + 1;
	  din_v <= 1;
       end
		
   completion_buffer dut (/*AUTOINST*/
			  // Outputs
			  .i_rdy		(i_rdy),
			  .dout			(dout[w_din-1:0]),
			  .dout_v		(dout_v),
			  // Inputs
			  .clk			(clk),
			  .rst			(rst),
			  .din			(din[w_din-1:0]),
			  .din_v		(din_v),
			  .wr_addr		(wr_addr[log2size-1:0]));


endmodule // tb

completion_buffer/dump.vcd
$date
	Fri Dec 11 13:58:39 2009
$end
$version
	Icarus Verilog
$end
$timescale
	1s
$end
$scope module tb $end
$var wire 32 ! dout[31:0] $end
$var wire 1 " dout_v $end
$var wire 1 # i_rdy $end
$var reg 1 $ clk $end
$var reg 32 % din[31:0] $end
$var reg 1 & din_v $end
$var reg 1 ' rst $end
$var reg 3 ( wr_addr[2:0] $end
$scope module dut $end
$var wire 1 $ clk $end
$var wire 32 ) din[31:0] $end
$var wire 1 & din_v $end
$var wire 32 * dout[31:0] $end
$var wire 1 " dout_v $end
$var wire 1 + i_rdy $end
$var wire 1 ' rst $end
$var wire 3 , wr_addr[2:0] $end
$var wire 3 - log2size[2:0] $end
$var reg 32 . dout_rc[31:0] $end
$var reg 1 " dout_v_rc $end
$var reg 1 / dout_v_wc $end
$var reg 3 0 entry_cnt_rc[2:0] $end
$var reg 3 1 entry_cnt_wc[2:0] $end
$var reg 1 2 rd_happened $end
$var reg 4 3 rd_ptr_rc[3:0] $end
$var reg 4 4 rd_ptr_wc[3:0] $end
$var reg 1 5 vbit_rc $end
$var reg 4 6 wr_cnt_rc[3:0] $end
$var reg 4 7 wr_cnt_wc[3:0] $end
$upscope $end
$upscope $end
$enddefinitions $end
#0
$dumpvars
bx 7
bx 6
x5
bx 4
bx 3
x2
bx 1
bx 0
x/
bx .
b11 -
b111 ,
1+
bx *
b0 )
b111 (
1'
0&
b0 %
0$
1#
x"
bx !
$end
#5
b0 4
0/
b0 7
b0 1
b0 3
b0 6
b0 0
02
1$
#10
0$
#15
1$
#20
0$
#25
1$
#30
0$
#35
1$
#40
0$
#45
1$
#50
0$
#55
1$
#60
0$
#65
1$
#70
0$
#75
1$
#80
0$
#85
1$
#90
0$
#95
1$
#100
0$
#105
1$
#110
0'
0$
#115
b1 1
b1 7
1&
b0 (
b0 ,
b1 %
b1 )
12
0"
1$
#120
0$
#125
b10 1
b10 7
b1 6
b1 0
02
b1 (
b1 ,
b10 %
b10 )
1$
#130
0$
#135
1/
b1 4
b11 1
b11 7
b10 (
b10 ,
b11 %
b11 )
12
15
b1 !
b1 *
b1 .
b10 6
b10 0
1$
#140
0$
#145
b10 4
1/
b100 7
1"
b1 3
b11 6
b11 0
b11 (
b11 ,
b100 %
b100 )
1$
#150
0$
#155
b11 4
1/
b101 7
b100 (
b100 ,
b101 %
b101 )
b10 !
b10 *
b10 .
b10 3
b100 6
1$
#160
0$
#165
b100 4
1/
b110 7
b11 3
b101 6
b11 !
b11 *
b11 .
b101 (
b101 ,
b110 %
b110 )
1$
#170
0$
#175
b101 4
1/
b111 7
b110 (
b110 ,
b111 %
b111 )
b100 !
b100 *
b100 .
b100 3
b110 6
1$
#180
0$
#185
b110 4
1/
b1000 7
b101 3
b111 6
b101 !
b101 *
b101 .
b111 (
b111 ,
b1000 %
b1000 )
1$
#190
0$
#195
b111 4
1/
b1001 7
b0 (
b0 ,
b1001 %
b1001 )
b110 !
b110 *
b110 .
b110 3
b1000 6
1$
#200
0$
#205
b1000 4
1/
b1010 7
b111 3
b1001 6
b111 !
b111 *
b111 .
b1 (
b1 ,
b1010 %
b1010 )
1$
#210
0$
#215
0/
b1011 7
b10 (
b10 ,
b1011 %
b1011 )
b1000 !
b1000 *
b1000 .
b1000 3
b1010 6
1$
#220
0$
#225
b100 1
b1100 7
1/
b1001 4
0"
b1011 6
05
b1001 !
b1001 *
b1001 .
b11 (
b11 ,
b1100 %
b1100 )
1$
#230
0$
#235
b1010 4
1/
b1101 7
b100 (
b100 ,
b1101 %
b1101 )
1"
b1001 3
b1100 6
b100 0
1$
#240
0$
#245
b1011 4
1/
b1110 7
b1010 3
b1101 6
b1010 !
b1010 *
b1010 .
b101 (
b101 ,
b1110 %
b1110 )
1$
#250
0$
#255
b1100 4
1/
b1111 7
b110 (
b110 ,
b1111 %
b1111 )
b1011 !
b1011 *
b1011 .
b1011 3
b1110 6
1$
#260
0$
#265
b1101 4
1/
b0 7
b1100 3
b1111 6
b1100 !
b1100 *
b1100 .
b111 (
b111 ,
b10000 %
b10000 )
1$
#270
0$
#275
b1110 4
1/
b1 7
b0 (
b0 ,
b10001 %
b10001 )
b1101 !
b1101 *
b1101 .
b1101 3
b0 6
1$
#280
0$
#285
b1111 4
1/
b10 7
b1110 3
b1 6
b1110 !
b1110 *
b1110 .
b1 (
b1 ,
b10010 %
b10010 )
1$
#290
0$
#295
b0 4
1/
b11 7
b10 (
b10 ,
b10011 %
b10011 )
b1111 !
b1111 *
b1111 .
b1111 3
b10 6
1$
#300
0$
#305
0/
b100 7
b0 3
b11 6
b10000 !
b10000 *
b10000 .
b11 (
b11 ,
b10100 %
b10100 )
1$
#310
0$
#315
1/
b1 4
b101 1
b101 7
b100 (
b100 ,
b10101 %
b10101 )
15
b10001 !
b10001 *
b10001 .
0"
b100 6
1$
#320
0$
#325
b10 4
1/
b110 7
1"
b1 3
b101 6
b101 0
b101 (
b101 ,
b10110 %
b10110 )
1$
#330
0$
#335
b11 4
1/
b111 7
b110 (
b110 ,
b10111 %
b10111 )
b10010 !
b10010 *
b10010 .
b10 3
b110 6
1$
#340
0$
#345
b100 4
1/
b1000 7
b11 3
b111 6
b10011 !
b10011 *
b10011 .
b111 (
b111 ,
b11000 %
b11000 )
1$
#350
0$
#355
b101 4
1/
b1001 7
b0 (
b0 ,
b11001 %
b11001 )
b10100 !
b10100 *
b10100 .
b100 3
b1000 6
1$
#360
0$
#365
b110 4
1/
b1010 7
b101 3
b1001 6
b10101 !
b10101 *
b10101 .
b1 (
b1 ,
b11010 %
b11010 )
1$
#370
0$
#375
b111 4
1/
b1011 7
b10 (
b10 ,
b11011 %
b11011 )
b10110 !
b10110 *
b10110 .
b110 3
b1010 6
1$
#380
0$
#385
b1000 4
1/
b1100 7
b111 3
b1011 6
b10111 !
b10111 *
b10111 .
b11 (
b11 ,
b11100 %
b11100 )
1$
#390
0$
#395
0/
b1101 7
b100 (
b100 ,
b11101 %
b11101 )
b11000 !
b11000 *
b11000 .
b1000 3
b1100 6
1$
#400
0$
#405
b110 1
b1110 7
1/
b1001 4
0"
b1101 6
05
b11001 !
b11001 *
b11001 .
b101 (
b101 ,
b11110 %
b11110 )
1$
#410
0$
#415
b1010 4
1/
b1111 7
b110 (
b110 ,
b11111 %
b11111 )
1"
b1001 3
b1110 6
b110 0
1$
#420
0$
#425
b1011 4
1/
b0 7
b1010 3
b1111 6
b11010 !
b11010 *
b11010 .
b111 (
b111 ,
b100000 %
b100000 )
1$
#430
0$
#435
b1100 4
1/
b1 7
b0 (
b0 ,
b100001 %
b100001 )
b11011 !
b11011 *
b11011 .
b1011 3
b0 6
1$
#440
0$
#445
b1101 4
1/
b10 7
b1100 3
b1 6
b11100 !
b11100 *
b11100 .
b1 (
b1 ,
b100010 %
b100010 )
1$
#450
0$
#455
b1110 4
1/
b11 7
b10 (
b10 ,
b100011 %
b100011 )
b11101 !
b11101 *
b11101 .
b1101 3
b10 6
1$
#460
0$
#465
b1111 4
1/
b100 7
b1110 3
b11 6
b11110 !
b11110 *
b11110 .
b11 (
b11 ,
b100100 %
b100100 )
1$
#470
0$
#475
b0 4
1/
b101 7
b100 (
b100 ,
b100101 %
b100101 )
b11111 !
b11111 *
b11111 .
b1111 3
b100 6
1$
#480
0$
#485
0/
b110 7
b0 3
b101 6
b100000 !
b100000 *
b100000 .
b101 (
b101 ,
b100110 %
b100110 )
1$
#490
0$
#495
1/
b1 4
b111 1
b111 7
b110 (
b110 ,
b100111 %
b100111 )
15
b100001 !
b100001 *
b100001 .
0"
b110 6
1$
#500
0$
#505
b10 4
1/
b1000 7
1"
b1 3
b111 6
b111 0
b111 (
b111 ,
b101000 %
b101000 )
1$
#510
0$
#515
b11 4
1/
b1001 7
b0 (
b0 ,
b101001 %
b101001 )
b100010 !
b100010 *
b100010 .
b10 3
b1000 6
1$
#520
0$
#525
b100 4
1/
b1010 7
b11 3
b1001 6
b100011 !
b100011 *
b100011 .
b1 (
b1 ,
b101010 %
b101010 )
1$
#530
0$
#535
b101 4
1/
b1011 7
b10 (
b10 ,
b101011 %
b101011 )
b100100 !
b100100 *
b100100 .
b100 3
b1010 6
1$
#540
0$
#545
b110 4
1/
b1100 7
b101 3
b1011 6
b100101 !
b100101 *
b100101 .
b11 (
b11 ,
b101100 %
b101100 )
1$
#550
0$
#555
b111 4
1/
b1101 7
b100 (
b100 ,
b101101 %
b101101 )
b100110 !
b100110 *
b100110 .
b110 3
b1100 6
1$
#560
0$
#565
b1000 4
1/
b1110 7
b111 3
b1101 6
b100111 !
b100111 *
b100111 .
b101 (
b101 ,
b101110 %
b101110 )
1$
#570
0$
#575
0/
b1111 7
b110 (
b110 ,
b101111 %
b101111 )
b101000 !
b101000 *
b101000 .
b1000 3
b1110 6
1$
#580
0$
#585
b0 1
b0 7
1/
b1001 4
0"
b1111 6
05
b101001 !
b101001 *
b101001 .
b111 (
b111 ,
b110000 %
b110000 )
1$
#590
0$
#595
b1010 4
1/
b1 7
b0 (
b0 ,
b110001 %
b110001 )
1"
b1001 3
b0 6
b0 0
1$
#600
0$
#605
b1011 4
1/
b10 7
b1010 3
b1 6
b101010 !
b101010 *
b101010 .
b1 (
b1 ,
b110010 %
b110010 )
1$
#610
0$
#615
b1100 4
1/
b11 7
b10 (
b10 ,
b110011 %
b110011 )
b101011 !
b101011 *
b101011 .
b1011 3
b10 6
1$
#620
0$
#625
b1101 4
1/
b100 7
b1100 3
b11 6
b101100 !
b101100 *
b101100 .
b11 (
b11 ,
b110100 %
b110100 )
1$
#630
0$
#635
b1110 4
1/
b101 7
b100 (
b100 ,
b110101 %
b110101 )
b101101 !
b101101 *
b101101 .
b1101 3
b100 6
1$
#640
0$
#645
b1111 4
1/
b110 7
b1110 3
b101 6
b101110 !
b101110 *
b101110 .
b101 (
b101 ,
b110110 %
b110110 )
1$
#650
0$
#655
b0 4
1/
b111 7
b110 (
b110 ,
b110111 %
b110111 )
b101111 !
b101111 *
b101111 .
b1111 3
b110 6
1$
#660
0$
#665
0/
b1000 7
b0 3
b111 6
b110000 !
b110000 *
b110000 .
b111 (
b111 ,
b111000 %
b111000 )
1$
#670
0$
#675
1/
b1 4
b1 1
b1001 7
b0 (
b0 ,
b111001 %
b111001 )
15
b110001 !
b110001 *
b110001 .
0"
b1000 6
1$
#680
0$
#685
0/
b1010 7
1"
b1 3
b1001 6
b1 0
02
b1 (
b1 ,
b111010 %
b111010 )
1$
#690
0$
#695
b10 1
b1011 7
b10 (
b10 ,
b111011 %
b111011 )
0"
b1010 6
1$
#700
0$
#705
b11 1
b1100 7
b1011 6
b10 0
12
05
b111010 !
b111010 *
b111010 .
b11 (
b11 ,
b111100 %
b111100 )
1$
#710
0$
#715
b100 1
b1101 7
b100 (
b100 ,
b111101 %
b111101 )
b1100 6
b11 0
1$
#720
0$
#725
b101 1
b1110 7
b1101 6
b100 0
b101 (
b101 ,
b111110 %
b111110 )
1$
#730
0$
#735
b110 1
b1111 7
b110 (
b110 ,
b111111 %
b111111 )
b1110 6
b101 0
1$
#740
0$
#745
b111 1
b0 7
b1111 6
b110 0
b111 (
b111 ,
b1000000 %
b1000000 )
1$
#750
0$
#755
b0 1
b1 7
b0 (
b0 ,
b1000001 %
b1000001 )
b0 6
b111 0
1$
#760
0$
#765
b1 1
b10 7
b1 6
b0 0
b1 (
b1 ,
b1000010 %
b1000010 )
1$
#770
0$
#775
b10 1
b11 7
b10 (
b10 ,
b1000011 %
b1000011 )
02
b10 6
b1 0
1$
#780
0$
#785
b11 1
b100 7
1/
b10 4
b11 6
b10 0
12
15
b1000010 !
b1000010 *
b1000010 .
b11 (
b11 ,
b1000100 %
b1000100 )
1$
#790
0$
#795
b11 4
1/
b101 7
b100 (
b100 ,
b1000101 %
b1000101 )
1"
b10 3
b100 6
b11 0
1$
#800
0$
#805
b100 4
1/
b110 7
b11 3
b101 6
b1000011 !
b1000011 *
b1000011 .
b101 (
b101 ,
b1000110 %
b1000110 )
1$
#810
0$
#815
b101 4
1/
b111 7
b110 (
b110 ,
b1000111 %
b1000111 )
b1000100 !
b1000100 *
b1000100 .
b100 3
b110 6
1$
#820
0$
#825
b110 4
1/
b1000 7
b101 3
b111 6
b1000101 !
b1000101 *
b1000101 .
b111 (
b111 ,
b1001000 %
b1001000 )
1$
#830
0$
#835
b111 4
1/
b1001 7
b0 (
b0 ,
b1001001 %
b1001001 )
b1000110 !
b1000110 *
b1000110 .
b110 3
b1000 6
1$
#840
0$
#845
b1000 4
1/
b1010 7
b111 3
b1001 6
b1000111 !
b1000111 *
b1000111 .
b1 (
b1 ,
b1001010 %
b1001010 )
1$
#850
0$
#855
0/
b1011 7
b10 (
b10 ,
b1001011 %
b1001011 )
b1001000 !
b1001000 *
b1001000 .
b1000 3
b1010 6
1$
#860
0$
#865
b100 1
b1100 7
1/
b1001 4
0"
b1011 6
05
b1001001 !
b1001001 *
b1001001 .
b11 (
b11 ,
b1001100 %
b1001100 )
1$
#870
0$
#875
b1010 4
1/
b1101 7
b100 (
b100 ,
b1001101 %
b1001101 )
1"
b1001 3
b1100 6
b100 0
1$
#880
0$
#885
b1011 4
1/
b1110 7
b1010 3
b1101 6
b1001010 !
b1001010 *
b1001010 .
b101 (
b101 ,
b1001110 %
b1001110 )
1$
#890
0$
#895
b1100 4
1/
b1111 7
b110 (
b110 ,
b1001111 %
b1001111 )
b1001011 !
b1001011 *
b1001011 .
b1011 3
b1110 6
1$
#900
0$
#905
b1101 4
1/
b0 7
b1100 3
b1111 6
b1001100 !
b1001100 *
b1001100 .
b111 (
b111 ,
b1010000 %
b1010000 )
1$
#910
0$
#915
b1110 4
1/
b1 7
b0 (
b0 ,
b1010001 %
b1010001 )
b1001101 !
b1001101 *
b1001101 .
b1101 3
b0 6
1$
#920
0$
#925
b1111 4
1/
b10 7
b1110 3
b1 6
b1001110 !
b1001110 *
b1001110 .
b1 (
b1 ,
b1010010 %
b1010010 )
1$
#930
0$
#935
b0 4
1/
b11 7
b10 (
b10 ,
b1010011 %
b1010011 )
b1001111 !
b1001111 *
b1001111 .
b1111 3
b10 6
1$
#940
0$
#945
0/
b100 7
b0 3
b11 6
b1010000 !
b1010000 *
b1010000 .
b11 (
b11 ,
b1010100 %
b1010100 )
1$
#950
0$
#955
1/
b1 4
b101 1
b101 7
b100 (
b100 ,
b1010101 %
b1010101 )
15
b1010001 !
b1010001 *
b1010001 .
0"
b100 6
1$
#960
0$
#965
b10 4
1/
b110 7
1"
b1 3
b101 6
b101 0
b101 (
b101 ,
b1010110 %
b1010110 )
1$
#970
0$
#975
b11 4
1/
b111 7
b110 (
b110 ,
b1010111 %
b1010111 )
b1010010 !
b1010010 *
b1010010 .
b10 3
b110 6
1$
#980
0$
#985
b100 4
1/
b1000 7
b11 3
b111 6
b1010011 !
b1010011 *
b1010011 .
b111 (
b111 ,
b1011000 %
b1011000 )
1$
#990
0$
#995
b101 4
1/
b1001 7
b0 (
b0 ,
b1011001 %
b1011001 )
b1010100 !
b1010100 *
b1010100 .
b100 3
b1000 6
1$
#1000
0$
#1005
b110 4
1/
b1010 7
b101 3
b1001 6
b1010101 !
b1010101 *
b1010101 .
b1 (
b1 ,
b1011010 %
b1011010 )
1$
#1010
0$
#1015
b111 4
1/
b1011 7
b10 (
b10 ,
b1011011 %
b1011011 )
b1010110 !
b1010110 *
b1010110 .
b110 3
b1010 6
1$
#1020
0$
#1025
b1000 4
1/
b1100 7
b111 3
b1011 6
b1010111 !
b1010111 *
b1010111 .
b11 (
b11 ,
b1011100 %
b1011100 )
1$
#1030
0$
#1035
0/
b1101 7
b100 (
b100 ,
b1011101 %
b1011101 )
b1011000 !
b1011000 *
b1011000 .
b1000 3
b1100 6
1$
#1040
0$
#1045
b110 1
b1110 7
1/
b1001 4
0"
b1101 6
05
b1011001 !
b1011001 *
b1011001 .
b101 (
b101 ,
b1011110 %
b1011110 )
1$
#1050
0$
#1055
b1010 4
1/
b1111 7
b110 (
b110 ,
b1011111 %
b1011111 )
1"
b1001 3
b1110 6
b110 0
1$
#1060
0$
#1065
b1011 4
1/
b0 7
b1010 3
b1111 6
b1011010 !
b1011010 *
b1011010 .
b111 (
b111 ,
b1100000 %
b1100000 )
1$
#1070
0$
#1075
b1100 4
1/
b1 7
b0 (
b0 ,
b1100001 %
b1100001 )
b1011011 !
b1011011 *
b1011011 .
b1011 3
b0 6
1$
#1080
0$
#1085
b1101 4
1/
b10 7
b1100 3
b1 6
b1011100 !
b1011100 *
b1011100 .
b1 (
b1 ,
b1100010 %
b1100010 )
1$
#1090
0$
#1095
b1110 4
1/
b11 7
b10 (
b10 ,
b1100011 %
b1100011 )
b1011101 !
b1011101 *
b1011101 .
b1101 3
b10 6
1$
#1100
0$
#1105
b1111 4
1/
b100 7
b1110 3
b11 6
b1011110 !
b1011110 *
b1011110 .
b11 (
b11 ,
b1100100 %
b1100100 )
1$
#1110
0$
#1115
b0 4
1/
b101 7
b100 (
b100 ,
b1100101 %
b1100101 )
b1011111 !
b1011111 *
b1011111 .
b1111 3
b100 6
1$
#1120
0$
#1125
0/
b110 7
b0 3
b101 6
b1100000 !
b1100000 *
b1100000 .
b101 (
b101 ,
b1100110 %
b1100110 )
1$
#1130
0$
#1135
1/
b1 4
b111 1
b111 7
b110 (
b110 ,
b1100111 %
b1100111 )
15
b1100001 !
b1100001 *
b1100001 .
0"
b110 6
1$
#1140
0$
#1145
b10 4
1/
b1000 7
1"
b1 3
b111 6
b111 0
b111 (
b111 ,
b1101000 %
b1101000 )
1$
#1150
0$
#1155
b11 4
1/
b1001 7
b0 (
b0 ,
b1101001 %
b1101001 )
b1100010 !
b1100010 *
b1100010 .
b10 3
b1000 6
1$
#1160
0$
#1165
b100 4
1/
b1010 7
b11 3
b1001 6
b1100011 !
b1100011 *
b1100011 .
b1 (
b1 ,
b1101010 %
b1101010 )
1$
#1170
0$
#1175
b101 4
1/
b1011 7
b10 (
b10 ,
b1101011 %
b1101011 )
b1100100 !
b1100100 *
b1100100 .
b100 3
b1010 6
1$
#1180
0$
#1185
b110 4
1/
b1100 7
b101 3
b1011 6
b1100101 !
b1100101 *
b1100101 .
b11 (
b11 ,
b1101100 %
b1101100 )
1$
#1190
0$
#1195
b111 4
1/
b1101 7
b100 (
b100 ,
b1101101 %
b1101101 )
b1100110 !
b1100110 *
b1100110 .
b110 3
b1100 6
1$
#1200
0$
#1205
b1000 4
1/
b1110 7
b111 3
b1101 6
b1100111 !
b1100111 *
b1100111 .
b101 (
b101 ,
b1101110 %
b1101110 )
1$
#1210
0$
#1215
0/
b1111 7
b110 (
b110 ,
b1101111 %
b1101111 )
b1101000 !
b1101000 *
b1101000 .
b1000 3
b1110 6
1$
#1220
0$
#1225
b0 1
b0 7
1/
b1001 4
0"
b1111 6
05
b1101001 !
b1101001 *
b1101001 .
b111 (
b111 ,
b1110000 %
b1110000 )
1$
#1230
0$
#1235
b1010 4
1/
b1 7
b0 (
b0 ,
b1110001 %
b1110001 )
1"
b1001 3
b0 6
b0 0
1$
#1240
0$
#1245
b1011 4
1/
b10 7
b1010 3
b1 6
b1101010 !
b1101010 *
b1101010 .
b1 (
b1 ,
b1110010 %
b1110010 )
1$
#1250
0$
#1255
b1100 4
1/
b11 7
b10 (
b10 ,
b1110011 %
b1110011 )
b1101011 !
b1101011 *
b1101011 .
b1011 3
b10 6
1$
#1260
0$
#1265
b1101 4
1/
b100 7
b1100 3
b11 6
b1101100 !
b1101100 *
b1101100 .
b11 (
b11 ,
b1110100 %
b1110100 )
1$
#1270
0$
#1275
b1110 4
1/
b101 7
b100 (
b100 ,
b1110101 %
b1110101 )
b1101101 !
b1101101 *
b1101101 .
b1101 3
b100 6
1$
#1280
0$
#1285
b1111 4
1/
b110 7
b1110 3
b101 6
b1101110 !
b1101110 *
b1101110 .
b101 (
b101 ,
b1110110 %
b1110110 )
1$
#1290
0$
#1295
b0 4
1/
b111 7
b110 (
b110 ,
b1110111 %
b1110111 )
b1101111 !
b1101111 *
b1101111 .
b1111 3
b110 6
1$
#1300
0$
#1305
0/
b1000 7
b0 3
b111 6
b1110000 !
b1110000 *
b1110000 .
b111 (
b111 ,
b1111000 %
b1111000 )
1$
#1310
0$
#1315
1/
b1 4
b1 1
b1001 7
b0 (
b0 ,
b1111001 %
b1111001 )
15
b1110001 !
b1110001 *
b1110001 .
0"
b1000 6
1$
#1320
0$
#1325
0/
b1010 7
1"
b1 3
b1001 6
b1 0
02
b1 (
b1 ,
b1111010 %
b1111010 )
1$
#1330
0$
#1335
b10 1
b1011 7
b10 (
b10 ,
b1111011 %
b1111011 )
0"
b1010 6
1$
#1340
0$
#1345
b11 1
b1100 7
b1011 6
b10 0
12
05
b1111010 !
b1111010 *
b1111010 .
b11 (
b11 ,
b1111100 %
b1111100 )
1$
#1350
0$
#1355
b100 1
b1101 7
b100 (
b100 ,
b1111101 %
b1111101 )
b1100 6
b11 0
1$
#1360
0$
#1365
b101 1
b1110 7
b1101 6
b100 0
b101 (
b101 ,
b1111110 %
b1111110 )
1$
#1370
0$
#1375
b110 1
b1111 7
b110 (
b110 ,
b1111111 %
b1111111 )
b1110 6
b101 0
1$
#1380
0$
#1385
b111 1
b0 7
b1111 6
b110 0
b111 (
b111 ,
b10000000 %
b10000000 )
1$
#1390
0$
#1395
b0 1
b1 7
b0 (
b0 ,
b10000001 %
b10000001 )
b0 6
b111 0
1$
#1400
0$
#1405
b1 1
b10 7
b1 6
b0 0
b1 (
b1 ,
b10000010 %
b10000010 )
1$
#1410
0$
#1415
b10 1
b11 7
b10 (
b10 ,
b10000011 %
b10000011 )
02
b10 6
b1 0
1$
#1420
0$
#1425
b11 1
b100 7
1/
b10 4
b11 6
b10 0
12
15
b10000010 !
b10000010 *
b10000010 .
b11 (
b11 ,
b10000100 %
b10000100 )
1$
#1430
0$
#1435
b11 4
1/
b101 7
b100 (
b100 ,
b10000101 %
b10000101 )
1"
b10 3
b100 6
b11 0
1$
#1440
0$
#1445
b100 4
1/
b110 7
b11 3
b101 6
b10000011 !
b10000011 *
b10000011 .
b101 (
b101 ,
b10000110 %
b10000110 )
1$
#1450
0$
#1455
b101 4
1/
b111 7
b110 (
b110 ,
b10000111 %
b10000111 )
b10000100 !
b10000100 *
b10000100 .
b100 3
b110 6
1$
#1460
0$
#1465
b110 4
1/
b1000 7
b101 3
b111 6
b10000101 !
b10000101 *
b10000101 .
b111 (
b111 ,
b10001000 %
b10001000 )
1$
#1470
0$
#1475
b111 4
1/
b1001 7
b0 (
b0 ,
b10001001 %
b10001001 )
b10000110 !
b10000110 *
b10000110 .
b110 3
b1000 6
1$
#1480
0$
#1485
b1000 4
1/
b1010 7
b111 3
b1001 6
b10000111 !
b10000111 *
b10000111 .
b1 (
b1 ,
b10001010 %
b10001010 )
1$
#1490
0$
#1495
0/
b1011 7
b10 (
b10 ,
b10001011 %
b10001011 )
b10001000 !
b10001000 *
b10001000 .
b1000 3
b1010 6
1$
#1500
0$
#1505
b100 1
b1100 7
1/
b1001 4
0"
b1011 6
05
b10001001 !
b10001001 *
b10001001 .
b11 (
b11 ,
b10001100 %
b10001100 )
1$
#1510
0$
#1515
b1010 4
1/
b1101 7
b100 (
b100 ,
b10001101 %
b10001101 )
1"
b1001 3
b1100 6
b100 0
1$
#1520
0$
#1525
b1011 4
1/
b1110 7
b1010 3
b1101 6
b10001010 !
b10001010 *
b10001010 .
b101 (
b101 ,
b10001110 %
b10001110 )
1$
#1530
0$
#1535
b1100 4
1/
b1111 7
b110 (
b110 ,
b10001111 %
b10001111 )
b10001011 !
b10001011 *
b10001011 .
b1011 3
b1110 6
1$
#1540
0$
#1545
b1101 4
1/
b0 7
b1100 3
b1111 6
b10001100 !
b10001100 *
b10001100 .
b111 (
b111 ,
b10010000 %
b10010000 )
1$
#1550
0$
#1555
b1110 4
1/
b1 7
b0 (
b0 ,
b10010001 %
b10010001 )
b10001101 !
b10001101 *
b10001101 .
b1101 3
b0 6
1$
#1560
0$
#1565
b1111 4
1/
b10 7
b1110 3
b1 6
b10001110 !
b10001110 *
b10001110 .
b1 (
b1 ,
b10010010 %
b10010010 )
1$
#1570
0$
#1575
b0 4
1/
b11 7
b10 (
b10 ,
b10010011 %
b10010011 )
b10001111 !
b10001111 *
b10001111 .
b1111 3
b10 6
1$
#1580
0$
#1585
0/
b100 7
b0 3
b11 6
b10010000 !
b10010000 *
b10010000 .
b11 (
b11 ,
b10010100 %
b10010100 )
1$
#1590
0$
#1595
1/
b1 4
b101 1
b101 7
b100 (
b100 ,
b10010101 %
b10010101 )
15
b10010001 !
b10010001 *
b10010001 .
0"
b100 6
1$
#1600
0$
#1605
b10 4
1/
b110 7
1"
b1 3
b101 6
b101 0
b101 (
b101 ,
b10010110 %
b10010110 )
1$
#1610
0$
